ccstorage/__init__.py
ccstorage-2.0.dist-info/METADATA
ccstorage-2.0.dist-info/WHEEL
ccstorage-2.0.dist-info/top_level.txt
ccstorage-2.0.dist-info/RECORD
