Metadata-Version: 2.1
Name: ccstorage
Version: 2.0
Summary: Local storage: CCStorage, and simple local file string read/write: CCIO
Home-page: 
Author: OpenFibers
Author-email: openfibers@gmail.com
License: MIT
